LICENSE
MANIFEST.in
README.rst
setup.py
ndb_x.egg-info/PKG-INFO
ndb_x.egg-info/SOURCES.txt
ndb_x.egg-info/dependency_links.txt
ndb_x.egg-info/not-zip-safe
ndb_x.egg-info/top_level.txt
ndbx/__init__.py
ndbx/futures.py
ndbx/locks.py
ndbx/utils.py