Metadata-Version: 1.0
Name: ndb-x
Version: 0.0.1
Summary: Synchronization primitives for ndb tasklets on Google App Engine (GAE)
Home-page: https://github.com/kaste/ndb-x
Author: herr kaste
Author-email: herr.kaste@gmail.com
License: MIT
Platform: linux
Platform: osx
Platform: win32
Classifier: Development Status :: 4 - Beta
Classifier: Intended Audience :: Developers
Classifier: License :: OSI Approved :: MIT License
Classifier: Operating System :: POSIX
Classifier: Operating System :: Microsoft :: Windows
Classifier: Operating System :: MacOS :: MacOS X
Classifier: Topic :: Software Development :: Testing
Classifier: Topic :: Software Development :: Quality Assurance
Classifier: Topic :: Utilities
Classifier: Programming Language :: Python
